debiai_data_provider/__init__.py
debiai_data_provider/app.py
debiai_data_provider/data_provider.py
debiai_data_provider/version.py
debiai_data_provider/controller/__init__.py
debiai_data_provider/controller/routes.py
debiai_data_provider/models/__init__.py
debiai_data_provider/models/debiai.py
debiai_data_provider/models/project.py
debiai_data_provider/providers/__init__.py
debiai_data_provider/providers/parquet_data_provider.py
debiai_data_provider/utils/__init__.py
debiai_data_provider/utils/parser.py
tests/__init__.py
tests/test_parquet_data_provider.py
tests/test_utils.py
debiai_data_provider-1.1.3.dist-info/LICENSE
debiai_data_provider-1.1.3.dist-info/METADATA
debiai_data_provider-1.1.3.dist-info/WHEEL
debiai_data_provider-1.1.3.dist-info/top_level.txt
debiai_data_provider-1.1.3.dist-info/RECORD
