Metadata-Version: 2.1
Name: debiai-data-provider
Version: 1.1.3
Summary: Start your own Data-provider from simple Python
Home-page: https://github.com/debiai/easy-data-provider
Requires-Python: >=3.7
License-File: LICENSE
Requires-Dist: pandas==2.2.3
Requires-Dist: fastapi==0.115.4
Requires-Dist: uvicorn==0.32.0
Requires-Dist: rich==13.9.4
